settings/__init__.py
settings/base.py
settings/types.py
settings/backend/__init__.py
settings/backend/config.py
settings/backend/datatype_loader.py
settings/backend/main.py
settings/backend/parsers/__init__.py
settings/backend/parsers/_template.py
settings/backend/parsers/cli.py
settings/backend/parsers/env.py
settings/backend/parsers/files.py
settings_gui/__init__.py
settings_gui/_tk_abstractor.py
settings_gui/config.py
settings_gui/tkinter/__init__.py
settings_gui/tkinter/lib.py
settings_gui/tkinter/main.py
settings_gui/tkinter/section_frames.py
settings_gui/tkinter/type_frames.py
settings_gui/tkinter/icons/checkmark-black.png
settings_gui/tkinter/icons/checkmark-white.png
settings_gui/tkinter/icons/error.png
settings_gui/tkinter/icons/folder-black.png
settings_gui/tkinter/icons/folder-white.png
settings_gui/ttk/__init__.py
object_settings-4.4.dist-info/METADATA
object_settings-4.4.dist-info/WHEEL
object_settings-4.4.dist-info/top_level.txt
object_settings-4.4.dist-info/RECORD
