Metadata-Version: 2.1
Name: object-settings
Version: 4.4
Summary: Simple object-oriented config library, where your settings are objects
License: MIT License
Project-URL: Homepage, https://github.com/SamuLumio/object-settings
Keywords: settings,setting,config,OOP,GUI
Classifier: Programming Language :: Python :: 3
Classifier: Operating System :: OS Independent
Classifier: Development Status :: 5 - Production/Stable
Classifier: License :: OSI Approved :: MIT License
Classifier: Typing :: Typed
Classifier: Intended Audience :: Developers
Classifier: Topic :: Utilities
Classifier: Topic :: Software Development
Classifier: Topic :: Software Development :: Libraries
Classifier: Topic :: Software Development :: Libraries :: Python Modules
Classifier: Topic :: Software Development :: User Interfaces
Requires-Dist: appdirs >=1.3.0
Requires-Dist: PyYAML
